<mediawiki xmlns="http://www.mediawiki.org/xml/export-0.10/" xmlns:xsi="http://www.w3.org/2001/XMLSchema-instance" xsi:schemaLocation="http://www.mediawiki.org/xml/export-0.10/ http://www.mediawiki.org/xml/export-0.10.xsd" version="0.10" xml:lang="en">
  <siteinfo>
    <sitename>Wikipedia</sitename>
    <dbname>enwiki</dbname>
    <base>https://en.wikipedia.org/wiki/Main_Page</base>
    <generator>MediaWiki 1.29.0-wmf.3</generator>
    <case>first-letter</case>
    <namespaces>
      <namespace key="-2" case="first-letter">Media</namespace>
      <namespace key="-1" case="first-letter">Special</namespace>
      <namespace key="0" case="first-letter" />
      <namespace key="1" case="first-letter">Talk</namespace>
      <namespace key="2" case="first-letter">User</namespace>
      <namespace key="3" case="first-letter">User talk</namespace>
      <namespace key="4" case="first-letter">Wikipedia</namespace>
      <namespace key="5" case="first-letter">Wikipedia talk</namespace>
      <namespace key="6" case="first-letter">File</namespace>
      <namespace key="7" case="first-letter">File talk</namespace>
      <namespace key="8" case="first-letter">MediaWiki</namespace>
      <namespace key="9" case="first-letter">MediaWiki talk</namespace>
      <namespace key="10" case="first-letter">Template</namespace>
      <namespace key="11" case="first-letter">Template talk</namespace>
      <namespace key="12" case="first-letter">Help</namespace>
      <namespace key="13" case="first-letter">Help talk</namespace>
      <namespace key="14" case="first-letter">Category</namespace>
      <namespace key="15" case="first-letter">Category talk</namespace>
      <namespace key="100" case="first-letter">Portal</namespace>
      <namespace key="101" case="first-letter">Portal talk</namespace>
      <namespace key="108" case="first-letter">Book</namespace>
      <namespace key="109" case="first-letter">Book talk</namespace>
      <namespace key="118" case="first-letter">Draft</namespace>
      <namespace key="119" case="first-letter">Draft talk</namespace>
      <namespace key="446" case="first-letter">Education Program</namespace>
      <namespace key="447" case="first-letter">Education Program talk</namespace>
      <namespace key="710" case="first-letter">TimedText</namespace>
      <namespace key="711" case="first-letter">TimedText talk</namespace>
      <namespace key="828" case="first-letter">Module</namespace>
      <namespace key="829" case="first-letter">Module talk</namespace>
      <namespace key="2300" case="first-letter">Gadget</namespace>
      <namespace key="2301" case="first-letter">Gadget talk</namespace>
      <namespace key="2302" case="case-sensitive">Gadget definition</namespace>
      <namespace key="2303" case="case-sensitive">Gadget definition talk</namespace>
    </namespaces>
  </siteinfo>
  <page>
    <title>Talk:Operation Copperhead</title>
    <ns>1</ns>
    <id>6598751</id>
    <revision>
      <id>722026135</id>
      <parentid>721987831</parentid>
      <timestamp>2016-05-25T14:21:21Z</timestamp>
      <contributor>
        <username>ErrantX</username>
        <id>1343284</id>
      </contributor>
      <comment>/* I was Monty's Treble */ +cmt</comment>
      <model>wikitext</model>
      <format>text/x-wiki</format>
      <text xml:space="preserve" bytes="2705">
{{talkheader}}
{{ArticleHistory
|action1=GAN
|action1date=09:33, 26 February 2013
|action1link=Talk:Operation Copperhead/GA1
|action1result=listed
|action1oldid=540565106
|dykdate=23 February 2013
|dykentry=... that '''[[Operation Copperhead]]''' saw [[M. E. Clifton James]] posing as Field Marshall [[Bernard Montgomery, 1st Viscount Montgomery of Alamein|Bernard Montgomery]] in the build up to [[D-Day]]?
|currentstatus=FA
|topic=warfare
|action2=WAR
|action2date=09:23, 16 August 2013 (UTC)
|action2link=Wikipedia:WikiProject Military history/Assessment/Operation Copperhead
|action2result=approved
|action2oldid=567240937
|maindate= 25 May 2016

|action3=FAC
|action3date=2015-11-14
|action3link=Wikipedia:Featured article candidates/Operation Copperhead/archive1
|action3result=promoted
|action3oldid=690513439
}}
{{WPMILHIST
|class = FA
|A-Class=pass
&lt;!-- B-Class-1. It is suitably referenced, and all major points have appropriate inline citations. --&gt;
|B-Class-1=yes
&lt;!-- B-Class-2. It reasonably covers the topic, and does not contain obvious omissions or inaccuracies. --&gt;
|B-Class-2=yes
&lt;!-- B-Class-3. It has a defined structure, including a lead section and one or more sections of content. --&gt;
|B-Class-3=yes
&lt;!-- B-Class-4. It is free from major grammatical errors. --&gt;
|B-Class-4=yes
&lt;!-- B-Class-5. It contains appropriate supporting materials, such as an infobox, images, or diagrams. --&gt;
|B-Class-5=yes
|British=y
|WWII=y
|Intel-task-force=yes}}

{{Talk:Operation Copperhead/GA1}}

== General, not Field Marshal ==

Montgomery became Field Marshal 01.08.1944. During Operation Copperhead he was General.  &lt;span style=&quot;font-size: smaller;&quot; class=&quot;autosigned&quot;&gt;— Preceding [[Wikipedia:Signatures|unsigned]] comment added by [[Special:Contributions/95.51.207.58|95.51.207.58]] ([[User talk:95.51.207.58|talk]]) 08:49, 28 February 2013 (UTC)&lt;/span&gt;&lt;!-- Template:Unsigned IP --&gt; &lt;!--Autosigned by SineBot--&gt;

== Anachronistic map ==

The map is of modern Europe; it'd be better to have one of Europe in 1944. [[User:Bthylafh|Bthylafh]] ([[User talk:Bthylafh|talk]]) 03:19, 25 May 2016 (UTC)

== I was Monty's Treble ==

The [[Goon Show]] did a skit episode called ''I was Monty's Treble'' in homage to this historical deception.

Is it worth mentioning this in the article???

[[User:Montalban|Montalban]] ([[User talk:Montalban|talk]]) 08:12, 25 May 2016 (UTC)
:I'd usually class stuff like that as pop culture; it would have to have (IMO) important context for the article (e.g. an unusual or new historical interpretation). On the flip side, it's worth mentioning in a Goon show article! --'''[[user:ErrantX|Errant]]''' &lt;sup&gt;([[User_talk:ErrantX|chat!]])&lt;/sup&gt; 14:21, 25 May 2016 (UTC)</text>
      <sha1>eb4uhyzhcmwam3q1tqeben80wc74393</sha1>
    </revision>
  </page>
</mediawiki>
